{
  "took" : 3,
  "timed_out" : false,
  "_shards" : {
    "total" : 5,
    "successful" : 5,
    "failed" : 0
  },
  "hits" : {
    "total" : 1,
    "max_score" : 1.0,
    "hits" : [ {
      "_index" : "757399",
      "_type" : "document",
      "_id" : "27850898",
      "_score" : 1.0,
      "_source":{"natural_id":"Contact;R_vehquJOKNtg5LoZ","_id_batch":3023040,"_id_document":27850898,"_id_source":"contact","_doc_date":"20150519","_doc_time":"20150519000000","time_of_day":"05:00","_doc_year":2015,"_doc_quarter":2,"_doc_month":5,"_doc_day_of_month":19,"_doc_week":21,"cb_content_type":"contentful","cb_content_subtype":"contentful","tran_endr_text":"no","mngr_nm":"williams,ronald s","tran_other_text":"no","comment_exists":"0","tran_update_info_text":"yes","tran_driver_text":"no","tran_address_text":"no","tran_vehicle_text":"no","report_region":"lakeland","all_rows":"segments","sat_agent_nbr":"4","tran_poc_text":"no","tran_payment_type_text":"no","response_id":"r_vehqujokntg5loz","region":"r6","policy_number":"4394473831","end_date":"20150519","asct_ful_nm":"edwards,hope p","tran_discount_text":"no","sctn_cd":"n823","tran_payment_text":"no","rated_state":"fl","sat_agent_nbr_box":"0","profit_center":"06 - lakeland","tran_coverage_text":"no","asct_id":"129565","natural_id_hash":"xgcCjNgzKiiqdK1l+bnPLFeuMPs="}
    } ]
  }
}
